tokenaligner/__init__.py
tokenaligner/aligner.py
tokenaligner-0.1.1.dist-info/METADATA
tokenaligner-0.1.1.dist-info/WHEEL
tokenaligner-0.1.1.dist-info/top_level.txt
tokenaligner-0.1.1.dist-info/RECORD
