Metadata-Version: 2.1
Name: tokenaligner
Version: 0.1.1
Summary: A lightweight utility to align NER labels with tokenized input for HuggingFace models.
Home-page: https://github.com/YatinChaudhary/tokenaligner
Author: Yatin Chaudhary
Author-email: yatinchaudhary91@gmail.com
License: UNKNOWN
Platform: UNKNOWN
Classifier: Programming Language :: Python :: 3
Classifier: License :: OSI Approved :: MIT License
Classifier: Operating System :: OS Independent
Requires-Python: >=3.7
Requires-Dist: datasets (>=2.0.0)
Requires-Dist: transformers (>=4.0.0)
